reso/__init__.py
reso/__main__.py
reso/palette.py
reso/regionmapper.py
reso/resoboard.py
reso-0.0.1.dist-info/LICENSE
reso-0.0.1.dist-info/METADATA
reso-0.0.1.dist-info/WHEEL
reso-0.0.1.dist-info/top_level.txt
reso-0.0.1.dist-info/RECORD
