Metadata-Version: 2.1
Name: reso
Version: 0.0.1
Summary: A digital logic circuit simulator that operates over images.
Home-page: https://gitlab.com/lynnpepin/reso
Author: lynndotpy
Author-email: lynn@lynndotpy.xyz
License: UNKNOWN
Project-URL: Bug Tracker, https://gitlab.com/lynnpepin/reso/issues
Platform: UNKNOWN
Classifier: Programming Language :: Python :: 3
Classifier: License :: OSI Approved :: MIT License
Classifier: Operating System :: OS Independent
Requires-Python: >=3.6
License-File: LICENSE
